langchain_googledrive/__init__.py
langchain_googledrive/document_loaders/__init__.py
langchain_googledrive/document_loaders/google_drive.py
langchain_googledrive/retrievers/__init__.py
langchain_googledrive/retrievers/google_drive.py
langchain_googledrive/tools/__init__.py
langchain_googledrive/tools/google_drive/__init__.py
langchain_googledrive/tools/google_drive/tool.py
langchain_googledrive/utilities/__init__.py
langchain_googledrive/utilities/google_drive.py
langchain_googledrive-0.3.3.dist-info/LICENSE.txt
langchain_googledrive-0.3.3.dist-info/METADATA
langchain_googledrive-0.3.3.dist-info/WHEEL
langchain_googledrive-0.3.3.dist-info/RECORD
