Metadata-Version: 2.3
Name: langchain-googledrive
Version: 0.3.3
Summary: This is a more advanced integration of Google Drive with langchain.
Home-page: https://www.github.com/pprados/langchain-googledrive
License: Apache 2.0
Author: Philippe PRADOS
Requires-Python: >=3.9,<4.0
Classifier: License :: Other/Proprietary License
Classifier: Programming Language :: Python :: 3
Classifier: Programming Language :: Python :: 3.9
Classifier: Programming Language :: Python :: 3.10
Classifier: Programming Language :: Python :: 3.11
Classifier: Programming Language :: Python :: 3.12
Classifier: Programming Language :: Python :: 3.13
Provides-Extra: all
Requires-Dist: google-api-python-client (>=2.97,<3.0)
Requires-Dist: google-auth-httplib2 (>=0.1)
Requires-Dist: google-auth-oauthlib (>=1.0)
Requires-Dist: langchain-openai (==0.3.3)
Requires-Dist: langchain_community (>=0.3.0)
Requires-Dist: langchain_core (>=0.3.0)
Project-URL: Repository, https://www.github.com/pprados/langchain-googledrive
